{"player":{"player_id":676439,"full_name":"Hunter Feduccia","bat_side":"L","pitch_hand":null,"primary_position":null,"team_id":null,"active":true},"form":{"hitter_id":676439,"form_signal":"normal","form_ratio":0.806,"last_7":{"k":6,"ab":14,"bb":3,"hr":0,"pa":17,"avg":0.1429,"obp":0.2941,"slg":0.1429,"hits":2,"games":7,"kRate":0.3529,"hrRate":0.0},"last_15":{"k":16,"ab":33,"bb":6,"hr":0,"pa":39,"avg":0.1515,"obp":0.2821,"slg":0.1515,"hits":5,"games":15,"kRate":0.4103,"hrRate":0.0},"last_30":{"k":27,"ab":72,"bb":12,"hr":0,"pa":85,"avg":0.1806,"obp":0.2941,"slg":0.2083,"hits":13,"games":30,"kRate":0.3176,"hrRate":0.0},"updated_at":"2026-04-18T14:59:30.552163"},"spray":{"hitter_id":676439,"pull_pct":0.5068,"center_pct":0.1359,"oppo_pct":0.3573,"deep_pct":0.5374,"shallow_pct":0.2303,"infield_pct":0.2323,"avg_exit_velo":87.51,"avg_launch_angle":16.31,"hr_pull_pct":0.0,"updated_at":"2026-04-18T14:59:35.866218","fb_lf_pct":0.4449,"fb_cf_pct":0.3529,"fb_rf_pct":0.2022},"similar":{"hitter_id":676439,"similar_list":[{"hitter_id":570267,"similarity":0.5992,"hitter_name":"Domingo Santana"},{"hitter_id":624407,"similarity":0.5972,"hitter_name":"Tzu-Wei Lin"},{"hitter_id":621514,"similarity":0.5702,"hitter_name":"Christin Stewart"},{"hitter_id":681508,"similarity":0.5345,"hitter_name":"Mickey Gasper"},{"hitter_id":676950,"similarity":0.5262,"hitter_name":"David MacKinnon"},{"hitter_id":669392,"similarity":0.525,"hitter_name":"Samad Taylor"},{"hitter_id":666152,"similarity":0.5078,"hitter_name":"David Hamilton"},{"hitter_id":665561,"similarity":0.5075,"hitter_name":"Rafael March\u00e1n"},{"hitter_id":673995,"similarity":0.4894,"hitter_name":"Davis Wendzel"},{"hitter_id":667452,"similarity":0.4888,"hitter_name":"Corey Julks"},{"hitter_id":681962,"similarity":0.4729,"hitter_name":"Vinny Capra"},{"hitter_id":519390,"similarity":0.4442,"hitter_name":"Stephen Vogt"},{"hitter_id":596059,"similarity":0.4376,"hitter_name":"Rougned Odor"},{"hitter_id":592200,"similarity":0.4251,"hitter_name":"Curt Casali"},{"hitter_id":624415,"similarity":0.4247,"hitter_name":"Cavan Biggio"},{"hitter_id":695391,"similarity":0.4183,"hitter_name":"Brett Harris"},{"hitter_id":506702,"similarity":0.4179,"hitter_name":"Sandy Le\u00f3n"},{"hitter_id":621450,"similarity":0.4157,"hitter_name":"Skye Bolt"},{"hitter_id":664056,"similarity":0.4102,"hitter_name":"Harrison Bader"},{"hitter_id":688363,"similarity":0.3949,"hitter_name":"Graham Pauley"}],"updated_at":"2026-04-18T14:59:37.022518"},"splits":[{"hitter_id":676439,"pitch_family":"changeup","season":2026,"pa":5,"ab":5,"hits":1,"hr":0,"bb":0,"k":2,"avg":0.2,"slg":0.2,"obp":0.2,"ops":0.4,"swing_pct":0.2308,"whiff_pct":0.3333,"avg_exit_velo":89.6,"avg_launch_angle":0.3,"hard_hit_pct":0.3333,"high_velo_whiff_pct":null,"high_spin_whiff_pct":null,"updated_at":"2026-04-20T16:13:10.263141","barrel_pct":null,"fb_pct":null,"ld_pct":null,"gb_pct":null},{"hitter_id":676439,"pitch_family":"fastball","season":2026,"pa":12,"ab":7,"hits":0,"hr":0,"bb":5,"k":3,"avg":0.0,"slg":0.0,"obp":0.4167,"ops":0.4167,"swing_pct":0.4884,"whiff_pct":0.2381,"avg_exit_velo":89.7,"avg_launch_angle":40.5,"hard_hit_pct":0.25,"high_velo_whiff_pct":0.125,"high_spin_whiff_pct":0.2857,"updated_at":"2026-04-18T14:57:57.713272","barrel_pct":null,"fb_pct":null,"ld_pct":null,"gb_pct":null},{"hitter_id":676439,"pitch_family":"cutter","season":2025,"pa":6,"ab":5,"hits":0,"hr":0,"bb":1,"k":1,"avg":0.0,"slg":0.0,"obp":0.1667,"ops":0.1667,"swing_pct":0.5676,"whiff_pct":0.1905,"avg_exit_velo":84.9,"avg_launch_angle":6.3,"hard_hit_pct":0.3333,"high_velo_whiff_pct":0.0,"high_spin_whiff_pct":0.2857,"updated_at":"2026-04-18T14:57:57.713272","barrel_pct":null,"fb_pct":null,"ld_pct":null,"gb_pct":null},{"hitter_id":676439,"pitch_family":"fastball","season":2025,"pa":40,"ab":31,"hits":5,"hr":0,"bb":8,"k":11,"avg":0.1613,"slg":0.2581,"obp":0.325,"ops":0.5831,"swing_pct":0.454,"whiff_pct":0.2027,"avg_exit_velo":94.1,"avg_launch_angle":23.5,"hard_hit_pct":0.5714,"high_velo_whiff_pct":0.2414,"high_spin_whiff_pct":0.2083,"updated_at":"2026-04-18T14:57:57.713272","barrel_pct":0.0476,"fb_pct":0.381,"ld_pct":0.3333,"gb_pct":0.2857},{"hitter_id":676439,"pitch_family":"sinker","season":2025,"pa":20,"ab":18,"hits":7,"hr":0,"bb":2,"k":2,"avg":0.3889,"slg":0.5,"obp":0.45,"ops":0.95,"swing_pct":0.2857,"whiff_pct":0.1667,"avg_exit_velo":89.8,"avg_launch_angle":13.1,"hard_hit_pct":0.3125,"high_velo_whiff_pct":0.1429,"high_spin_whiff_pct":0.1111,"updated_at":"2026-04-18T14:57:57.713272","barrel_pct":0.0,"fb_pct":0.25,"ld_pct":0.1875,"gb_pct":0.5625},{"hitter_id":676439,"pitch_family":"changeup","season":2025,"pa":12,"ab":12,"hits":0,"hr":0,"bb":0,"k":4,"avg":0.0,"slg":0.0,"obp":0.0,"ops":0.0,"swing_pct":0.4821,"whiff_pct":0.5926,"avg_exit_velo":75.1,"avg_launch_angle":10.2,"hard_hit_pct":0.0,"high_velo_whiff_pct":null,"high_spin_whiff_pct":0.75,"updated_at":"2026-04-18T14:57:57.713272","barrel_pct":0.0,"fb_pct":0.25,"ld_pct":0.125,"gb_pct":0.625},{"hitter_id":676439,"pitch_family":"slider","season":2025,"pa":16,"ab":12,"hits":0,"hr":0,"bb":3,"k":4,"avg":0.0,"slg":0.0,"obp":0.1875,"ops":0.1875,"swing_pct":0.3875,"whiff_pct":0.2581,"avg_exit_velo":85.7,"avg_launch_angle":25.3,"hard_hit_pct":0.1111,"high_velo_whiff_pct":0.4444,"high_spin_whiff_pct":0.25,"updated_at":"2026-04-18T14:57:57.713272","barrel_pct":0.0,"fb_pct":0.3333,"ld_pct":0.3333,"gb_pct":0.3333},{"hitter_id":676439,"pitch_family":"curveball","season":2025,"pa":8,"ab":7,"hits":1,"hr":0,"bb":1,"k":4,"avg":0.1429,"slg":0.1429,"obp":0.25,"ops":0.3929,"swing_pct":0.2549,"whiff_pct":0.3846,"avg_exit_velo":83.4,"avg_launch_angle":4.7,"hard_hit_pct":0.3333,"high_velo_whiff_pct":0.4286,"high_spin_whiff_pct":null,"updated_at":"2026-04-18T14:57:57.713272","barrel_pct":null,"fb_pct":null,"ld_pct":null,"gb_pct":null}],"recentProjections":[{"game_date":"2026-04-19","dk_pts":4.44,"fd_pts":6.58,"proj":{"h":0.66,"k":0.93,"r":0.46,"bb":0.78,"hr":0.0,"avg":0.2252,"rbi":0.23,"slg":0.3389},"factor_score":-0.25,"factors":{"park":0,"matchup":0,"platoon":-1,"weather":0,"recentForm":0,"battingOrder":-1,"stuffQuality":0}},{"game_date":"2026-04-18","dk_pts":5.25,"fd_pts":7.34,"proj":{"h":0.81,"k":0.58,"r":0.51,"bb":0.76,"hr":0.0,"avg":0.2751,"rbi":0.28,"slg":0.4016},"factor_score":-0.0,"factors":{"park":0,"matchup":0,"platoon":1,"weather":1,"recentForm":0,"battingOrder":-1,"stuffQuality":-1}},{"game_date":"2026-04-15","dk_pts":5.25,"fd_pts":7.45,"proj":{"h":0.76,"k":0.64,"r":0.52,"bb":0.86,"hr":0.0,"avg":0.2662,"rbi":0.27,"slg":0.3729},"factor_score":0.1,"factors":{"park":0,"matchup":0,"platoon":1,"weather":-1,"recentForm":0,"battingOrder":-1,"stuffQuality":0}},{"game_date":"2026-04-12","dk_pts":4.73,"fd_pts":6.73,"proj":{"h":0.71,"k":0.65,"r":0.47,"bb":0.74,"hr":0.0,"avg":0.249,"rbi":0.25,"slg":0.294},"factor_score":-0.15,"factors":{"park":-1,"matchup":0,"platoon":1,"weather":0,"recentForm":0,"battingOrder":-1,"stuffQuality":-1}},{"game_date":"2025-08-30","dk_pts":4.65,"fd_pts":6.75,"proj":{"h":0.63,"k":0.68,"r":0.47,"bb":0.87,"hr":0.0,"avg":0.2292,"rbi":0.22,"slg":0.3373},"factor_score":-0.05,"factors":{"park":0,"matchup":0,"platoon":1,"weather":0,"recentForm":0,"battingOrder":-1,"stuffQuality":-1}},{"game_date":"2025-08-27","dk_pts":4.85,"fd_pts":6.84,"proj":{"h":0.73,"k":0.58,"r":0.48,"bb":0.74,"hr":0.0,"avg":0.2561,"rbi":0.26,"slg":0.3152},"factor_score":-0.1,"factors":{"park":0,"matchup":0,"platoon":1,"weather":-1,"recentForm":0,"battingOrder":-1,"stuffQuality":-1}},{"game_date":"2025-08-25","dk_pts":4.54,"fd_pts":6.55,"proj":{"h":0.79,"k":0.91,"r":0.46,"bb":0.59,"hr":0.0,"avg":0.237,"rbi":0.27,"slg":0.2845},"factor_score":-0.35,"factors":{"park":0,"matchup":-1,"platoon":-1,"weather":-1,"recentForm":0,"battingOrder":-1,"stuffQuality":1}},{"game_date":"2025-08-22","dk_pts":5.8,"fd_pts":8.04,"proj":{"h":1.05,"k":0.81,"r":0.57,"bb":0.6,"hr":0.0,"avg":0.2992,"rbi":0.37,"slg":0.3978},"factor_score":0.6,"factors":{"park":1,"matchup":1,"platoon":1,"weather":1,"recentForm":0,"battingOrder":0,"stuffQuality":0}},{"game_date":"2025-08-20","dk_pts":5.71,"fd_pts":8.02,"proj":{"h":0.87,"k":0.66,"r":0.56,"bb":0.85,"hr":0.0,"avg":0.2673,"rbi":0.3,"slg":0.3609},"factor_score":0.15,"factors":{"park":1,"matchup":0,"platoon":1,"weather":1,"recentForm":0,"battingOrder":0,"stuffQuality":-1}},{"game_date":"2025-08-17","dk_pts":4.97,"fd_pts":7.27,"proj":{"h":0.69,"k":0.85,"r":0.5,"bb":0.91,"hr":0.0,"avg":0.2315,"rbi":0.24,"slg":0.3306},"factor_score":-0.0,"factors":{"park":0,"matchup":0,"platoon":1,"weather":1,"recentForm":0,"battingOrder":-1,"stuffQuality":-1}},{"game_date":"2025-08-15","dk_pts":4.82,"fd_pts":6.79,"proj":{"h":0.73,"k":0.58,"r":0.46,"bb":0.69,"hr":0.01,"avg":0.2494,"rbi":0.27,"slg":0.3631},"factor_score":-0.0,"factors":{"park":0,"matchup":0,"platoon":1,"weather":1,"recentForm":0,"battingOrder":-1,"stuffQuality":-1}},{"game_date":"2025-08-13","dk_pts":5.57,"fd_pts":7.78,"proj":{"h":0.86,"k":0.61,"r":0.54,"bb":0.8,"hr":0.0,"avg":0.2778,"rbi":0.3,"slg":0.3598},"factor_score":0.1,"factors":{"park":1,"matchup":0,"platoon":1,"weather":1,"recentForm":0,"battingOrder":-1,"stuffQuality":-1}},{"game_date":"2025-08-10","dk_pts":4.76,"fd_pts":6.75,"proj":{"h":0.86,"k":0.89,"r":0.47,"bb":0.51,"hr":0.0,"avg":0.2407,"rbi":0.31,"slg":0.268},"factor_score":0.4,"factors":{"park":0,"matchup":1,"platoon":1,"weather":-1,"recentForm":0,"battingOrder":0,"stuffQuality":0}},{"game_date":"2025-08-09","dk_pts":4.64,"fd_pts":6.72,"proj":{"h":0.75,"k":0.91,"r":0.45,"bb":0.62,"hr":0.02,"avg":0.2154,"rbi":0.28,"slg":0.2862},"factor_score":0.0,"factors":{"park":0,"matchup":0,"platoon":1,"weather":0,"recentForm":0,"battingOrder":0,"stuffQuality":-1}},{"game_date":"2025-08-08","dk_pts":4.52,"fd_pts":6.39,"proj":{"h":0.71,"k":0.64,"r":0.44,"bb":0.62,"hr":0.01,"avg":0.2168,"rbi":0.26,"slg":0.2553},"factor_score":-0.05,"factors":{"park":0,"matchup":0,"platoon":1,"weather":0,"recentForm":0,"battingOrder":-1,"stuffQuality":-1}},{"game_date":"2025-08-05","dk_pts":4.55,"fd_pts":6.73,"proj":{"h":0.61,"k":0.81,"r":0.47,"bb":0.89,"hr":0.0,"avg":0.2158,"rbi":0.21,"slg":0.291},"factor_score":0.1,"factors":{"park":1,"matchup":0,"platoon":1,"weather":1,"recentForm":0,"battingOrder":-1,"stuffQuality":-1}},{"game_date":"2025-08-03","dk_pts":5.78,"fd_pts":8.15,"proj":{"h":0.87,"k":0.71,"r":0.56,"bb":0.86,"hr":0.01,"avg":0.2688,"rbi":0.31,"slg":0.4078},"factor_score":0.15,"factors":{"park":1,"matchup":0,"platoon":1,"weather":1,"recentForm":0,"battingOrder":0,"stuffQuality":-1}},{"game_date":"2025-08-02","dk_pts":5.07,"fd_pts":7.0,"proj":{"h":0.89,"k":0.65,"r":0.48,"bb":0.51,"hr":0.02,"avg":0.2867,"rbi":0.33,"slg":0.3883},"factor_score":0.1,"factors":{"park":1,"matchup":0,"platoon":1,"weather":1,"recentForm":0,"battingOrder":-1,"stuffQuality":-1}}],"sprayHits":[{"hit_coord_x":139.0,"hit_coord_y":164.0,"event_type":"field_out","exit_velocity":67.2,"launch_angle":-46.0,"game_date":"2026-04-19"},{"hit_coord_x":95.34,"hit_coord_y":91.47,"event_type":"field_out","exit_velocity":85.0,"launch_angle":44.0,"game_date":"2026-04-19"},{"hit_coord_x":189.23,"hit_coord_y":112.17,"event_type":"single","exit_velocity":91.3,"launch_angle":16.0,"game_date":"2026-04-19"},{"hit_coord_x":150.8,"hit_coord_y":162.32,"event_type":"force_out","exit_velocity":84.1,"launch_angle":-33.0,"game_date":"2026-04-18"},{"hit_coord_x":191.99,"hit_coord_y":111.45,"event_type":"field_out","exit_velocity":76.7,"launch_angle":38.0,"game_date":"2026-04-15"},{"hit_coord_x":140.58,"hit_coord_y":83.87,"event_type":"single","exit_velocity":88.6,"launch_angle":14.0,"game_date":"2026-04-15"},{"hit_coord_x":75.8,"hit_coord_y":107.09,"event_type":"field_out","exit_velocity":90.0,"launch_angle":46.0,"game_date":"2026-04-12"},{"hit_coord_x":59.27,"hit_coord_y":85.98,"event_type":"field_out","exit_velocity":98.6,"launch_angle":21.0,"game_date":"2026-04-08"},{"hit_coord_x":189.31,"hit_coord_y":112.66,"event_type":"single","exit_velocity":93.5,"launch_angle":11.0,"game_date":"2026-04-05"},{"hit_coord_x":179.95,"hit_coord_y":125.85,"event_type":"single","exit_velocity":94.8,"launch_angle":11.0,"game_date":"2026-04-04"},{"hit_coord_x":79.38,"hit_coord_y":109.85,"event_type":"field_out","exit_velocity":85.3,"launch_angle":51.0,"game_date":"2026-04-04"},{"hit_coord_x":92.54,"hit_coord_y":64.3,"event_type":"field_out","exit_velocity":96.0,"launch_angle":20.0,"game_date":"2026-04-04"},{"hit_coord_x":151.75,"hit_coord_y":162.83,"event_type":"single","exit_velocity":89.1,"launch_angle":-1.0,"game_date":"2026-03-29"},{"hit_coord_x":147.64,"hit_coord_y":148.01,"event_type":"field_out","exit_velocity":76.3,"launch_angle":10.0,"game_date":"2025-09-28"},{"hit_coord_x":145.28,"hit_coord_y":160.72,"event_type":"field_out","exit_velocity":73.0,"launch_angle":2.0,"game_date":"2025-09-26"},{"hit_coord_x":106.64,"hit_coord_y":156.64,"event_type":"field_out","exit_velocity":68.5,"launch_angle":4.0,"game_date":"2025-09-26"},{"hit_coord_x":153.07,"hit_coord_y":135.54,"event_type":"field_out","exit_velocity":97.6,"launch_angle":10.0,"game_date":"2025-09-25"},{"hit_coord_x":160.94,"hit_coord_y":168.4,"event_type":"field_out","exit_velocity":91.7,"launch_angle":-18.0,"game_date":"2025-09-24"},{"hit_coord_x":174.11,"hit_coord_y":56.42,"event_type":"double","exit_velocity":103.7,"launch_angle":20.0,"game_date":"2025-09-24"},{"hit_coord_x":84.98,"hit_coord_y":150.32,"event_type":"field_out","exit_velocity":94.4,"launch_angle":9.0,"game_date":"2025-09-23"},{"hit_coord_x":91.98,"hit_coord_y":170.15,"event_type":"field_out","exit_velocity":87.9,"launch_angle":73.0,"game_date":"2025-09-23"},{"hit_coord_x":155.87,"hit_coord_y":149.15,"event_type":"field_out","exit_velocity":106.5,"launch_angle":1.0,"game_date":"2025-09-18"},{"hit_coord_x":127.49,"hit_coord_y":104.04,"event_type":"single","exit_velocity":71.6,"launch_angle":29.0,"game_date":"2025-09-18"},{"hit_coord_x":43.88,"hit_coord_y":117.22,"event_type":"double","exit_velocity":99.5,"launch_angle":-3.0,"game_date":"2025-09-16"},{"hit_coord_x":112.42,"hit_coord_y":43.32,"event_type":"field_out","exit_velocity":104.4,"launch_angle":23.0,"game_date":"2025-09-16"},{"hit_coord_x":78.34,"hit_coord_y":107.09,"event_type":"field_out","exit_velocity":86.5,"launch_angle":22.0,"game_date":"2025-09-16"},{"hit_coord_x":88.27,"hit_coord_y":83.37,"event_type":"single","exit_velocity":99.8,"launch_angle":9.0,"game_date":"2025-09-13"},{"hit_coord_x":116.64,"hit_coord_y":78.92,"event_type":"field_out","exit_velocity":89.1,"launch_angle":22.0,"game_date":"2025-09-11"},{"hit_coord_x":116.0,"hit_coord_y":148.0,"event_type":"field_out","exit_velocity":93.6,"launch_angle":6.0,"game_date":"2025-09-11"},{"hit_coord_x":140.16,"hit_coord_y":106.58,"event_type":"single","exit_velocity":99.2,"launch_angle":-0.0,"game_date":"2025-09-10"},{"hit_coord_x":179.65,"hit_coord_y":124.2,"event_type":"single","exit_velocity":84.2,"launch_angle":4.0,"game_date":"2025-09-09"},{"hit_coord_x":151.76,"hit_coord_y":163.75,"event_type":"field_out","exit_velocity":72.5,"launch_angle":-12.0,"game_date":"2025-09-09"},{"hit_coord_x":152.83,"hit_coord_y":164.35,"event_type":"field_out","exit_velocity":67.1,"launch_angle":69.0,"game_date":"2025-09-06"},{"hit_coord_x":59.08,"hit_coord_y":130.91,"event_type":"field_out","exit_velocity":88.8,"launch_angle":54.0,"game_date":"2025-09-05"},{"hit_coord_x":160.94,"hit_coord_y":163.84,"event_type":"field_out","exit_velocity":96.4,"launch_angle":-27.0,"game_date":"2025-09-05"},{"hit_coord_x":144.72,"hit_coord_y":101.52,"event_type":"single","exit_velocity":84.6,"launch_angle":8.0,"game_date":"2025-09-03"},{"hit_coord_x":153.34,"hit_coord_y":150.67,"event_type":"force_out","exit_velocity":80.6,"launch_angle":-2.0,"game_date":"2025-09-03"},{"hit_coord_x":157.9,"hit_coord_y":94.42,"event_type":"single","exit_velocity":101.4,"launch_angle":6.0,"game_date":"2025-09-03"},{"hit_coord_x":85.89,"hit_coord_y":104.99,"event_type":"sac_fly","exit_velocity":79.9,"launch_angle":25.0,"game_date":"2025-09-03"},{"hit_coord_x":148.78,"hit_coord_y":169.92,"event_type":"double_play","exit_velocity":94.0,"launch_angle":4.0,"game_date":"2025-09-02"},{"hit_coord_x":127.06,"hit_coord_y":139.57,"event_type":"field_out","exit_velocity":70.6,"launch_angle":9.0,"game_date":"2025-09-02"},{"hit_coord_x":85.94,"hit_coord_y":127.36,"event_type":"field_out","exit_velocity":88.1,"launch_angle":56.0,"game_date":"2025-08-31"},{"hit_coord_x":80.87,"hit_coord_y":171.45,"event_type":"field_out","exit_velocity":75.2,"launch_angle":64.0,"game_date":"2025-08-31"},{"hit_coord_x":104.18,"hit_coord_y":192.73,"event_type":"field_out","exit_velocity":90.0,"launch_angle":79.0,"game_date":"2025-08-30"},{"hit_coord_x":146.75,"hit_coord_y":163.84,"event_type":"field_out","exit_velocity":80.2,"launch_angle":-40.0,"game_date":"2025-08-30"},{"hit_coord_x":119.3,"hit_coord_y":138.45,"event_type":"field_out","exit_velocity":98.9,"launch_angle":9.0,"game_date":"2025-08-30"},{"hit_coord_x":106.91,"hit_coord_y":164.26,"event_type":"field_out","exit_velocity":79.5,"launch_angle":4.0,"game_date":"2025-08-27"},{"hit_coord_x":95.13,"hit_coord_y":152.31,"event_type":"field_out","exit_velocity":72.7,"launch_angle":13.0,"game_date":"2025-08-27"},{"hit_coord_x":129.29,"hit_coord_y":83.87,"event_type":"field_out","exit_velocity":87.8,"launch_angle":45.0,"game_date":"2025-08-25"},{"hit_coord_x":167.48,"hit_coord_y":66.66,"event_type":"sac_fly","exit_velocity":98.5,"launch_angle":38.0,"game_date":"2025-08-25"},{"hit_coord_x":65.89,"hit_coord_y":111.55,"event_type":"field_out","exit_velocity":79.7,"launch_angle":29.0,"game_date":"2025-08-22"},{"hit_coord_x":81.06,"hit_coord_y":110.08,"event_type":"field_out","exit_velocity":83.3,"launch_angle":22.0,"game_date":"2025-08-22"},{"hit_coord_x":112.29,"hit_coord_y":147.63,"event_type":"field_out","exit_velocity":73.2,"launch_angle":-3.0,"game_date":"2025-08-22"},{"hit_coord_x":146.75,"hit_coord_y":46.28,"event_type":"double","exit_velocity":102.8,"launch_angle":26.0,"game_date":"2025-08-20"},{"hit_coord_x":151.31,"hit_coord_y":155.23,"event_type":"field_out","exit_velocity":95.3,"launch_angle":1.0,"game_date":"2025-08-20"},{"hit_coord_x":148.31,"hit_coord_y":159.9,"event_type":"field_out","exit_velocity":84.7,"launch_angle":-17.0,"game_date":"2025-08-17"},{"hit_coord_x":141.65,"hit_coord_y":185.34,"event_type":"fielders_choice","exit_velocity":67.6,"launch_angle":-33.0,"game_date":"2025-08-17"},{"hit_coord_x":125.32,"hit_coord_y":203.09,"event_type":"double_play","exit_velocity":56.3,"launch_angle":-55.0,"game_date":"2025-08-17"},{"hit_coord_x":73.84,"hit_coord_y":45.84,"event_type":"double","exit_velocity":105.9,"launch_angle":18.0,"game_date":"2025-08-16"},{"hit_coord_x":141.76,"hit_coord_y":149.46,"event_type":"field_out","exit_velocity":104.7,"launch_angle":-23.0,"game_date":"2025-08-14"},{"hit_coord_x":113.74,"hit_coord_y":210.98,"event_type":"field_out","exit_velocity":80.5,"launch_angle":86.0,"game_date":"2025-08-10"},{"hit_coord_x":127.86,"hit_coord_y":74.52,"event_type":"field_out","exit_velocity":85.6,"launch_angle":33.0,"game_date":"2025-08-10"},{"hit_coord_x":86.49,"hit_coord_y":103.88,"event_type":"field_out","exit_velocity":92.7,"launch_angle":54.0,"game_date":"2025-08-10"},{"hit_coord_x":70.4,"hit_coord_y":160.71,"event_type":"field_out","exit_velocity":79.0,"launch_angle":67.0,"game_date":"2025-08-10"},{"hit_coord_x":183.17,"hit_coord_y":73.19,"event_type":"field_out","exit_velocity":105.9,"launch_angle":20.0,"game_date":"2025-08-10"},{"hit_coord_x":185.48,"hit_coord_y":106.46,"event_type":"single","exit_velocity":87.2,"launch_angle":3.0,"game_date":"2025-08-09"},{"hit_coord_x":166.92,"hit_coord_y":64.79,"event_type":"field_out","exit_velocity":96.7,"launch_angle":39.0,"game_date":"2025-08-09"},{"hit_coord_x":154.8,"hit_coord_y":159.18,"event_type":"field_out","exit_velocity":81.6,"launch_angle":-14.0,"game_date":"2025-08-06"},{"hit_coord_x":72.17,"hit_coord_y":123.7,"event_type":"double","exit_velocity":85.4,"launch_angle":-19.0,"game_date":"2025-08-06"},{"hit_coord_x":97.05,"hit_coord_y":130.82,"event_type":"field_out","exit_velocity":95.0,"launch_angle":7.0,"game_date":"2025-08-06"},{"hit_coord_x":162.36,"hit_coord_y":99.93,"event_type":"single","exit_velocity":108.7,"launch_angle":12.0,"game_date":"2025-08-03"},{"hit_coord_x":80.87,"hit_coord_y":165.36,"event_type":"field_out","exit_velocity":76.9,"launch_angle":69.0,"game_date":"2025-08-03"},{"hit_coord_x":57.21,"hit_coord_y":123.78,"event_type":"field_out","exit_velocity":83.4,"launch_angle":51.0,"game_date":"2025-08-02"},{"hit_coord_x":153.34,"hit_coord_y":154.22,"event_type":"field_out","exit_velocity":98.9,"launch_angle":-7.0,"game_date":"2025-04-07"},{"hit_coord_x":184.32,"hit_coord_y":115.52,"event_type":"single","exit_velocity":92.2,"launch_angle":7.0,"game_date":"2024-09-22"},{"hit_coord_x":147.82,"hit_coord_y":171.85,"event_type":"grounded_into_double_play","exit_velocity":72.3,"launch_angle":-3.0,"game_date":"2024-09-22"},{"hit_coord_x":70.17,"hit_coord_y":109.45,"event_type":"field_out","exit_velocity":80.7,"launch_angle":28.0,"game_date":"2024-09-22"},{"hit_coord_x":165.13,"hit_coord_y":74.11,"event_type":"field_out","exit_velocity":99.2,"launch_angle":45.0,"game_date":"2024-09-22"},{"hit_coord_x":172.9,"hit_coord_y":86.17,"event_type":"single","exit_velocity":102.1,"launch_angle":4.0,"game_date":"2024-09-17"},{"hit_coord_x":141.84,"hit_coord_y":163.88,"event_type":"field_out","exit_velocity":66.7,"launch_angle":-33.0,"game_date":"2024-09-17"},{"hit_coord_x":43.95,"hit_coord_y":109.17,"event_type":"single","exit_velocity":81.9,"launch_angle":3.0,"game_date":"2024-09-17"},{"hit_coord_x":145.05,"hit_coord_y":157.6,"event_type":"field_out","exit_velocity":72.3,"launch_angle":-8.0,"game_date":"2024-09-17"},{"hit_coord_x":178.87,"hit_coord_y":115.62,"event_type":"single","exit_velocity":82.6,"launch_angle":19.0,"game_date":"2024-08-25"},{"hit_coord_x":151.63,"hit_coord_y":80.38,"event_type":"field_out","exit_velocity":83.2,"launch_angle":32.0,"game_date":"2024-08-01"}]}