{"player":{"player_id":657277,"full_name":"Logan Webb","bat_side":"R","pitch_hand":"R","primary_position":null,"team_id":null,"active":true},"seasons":[{"pitcher_id":657277,"season":2026,"avg_ip":5.87,"avg_k":5.4,"avg_bb":2.2,"avg_h":6.2,"avg_hr":0.4,"fip":3.2,"games_started":5,"updated_at":"2026-04-18T14:58:19.042981","hr9_vs_l":1.095,"hr9_vs_r":0.0,"k_pct_vs_l":0.1892,"k_pct_vs_r":0.2241,"fb_pct_allowed":0.163,"barrel_pct_allowed":0.0549},{"pitcher_id":657277,"season":2025,"avg_ip":5.75,"avg_k":6.59,"avg_bb":1.35,"avg_h":6.18,"avg_hr":0.412,"fip":2.53,"games_started":34,"updated_at":"2026-04-18T14:58:19.042981","hr9_vs_l":0.736,"hr9_vs_r":0.554,"k_pct_vs_l":0.2419,"k_pct_vs_r":0.2797,"fb_pct_allowed":0.2021,"barrel_pct_allowed":0.0434},{"pitcher_id":657277,"season":2024,"avg_ip":5.86,"avg_k":5.21,"avg_bb":1.52,"avg_h":6.12,"avg_hr":0.333,"fip":3.02,"games_started":33,"updated_at":"2026-04-18T14:58:19.042981","hr9_vs_l":0.27,"hr9_vs_r":0.771,"k_pct_vs_l":0.222,"k_pct_vs_r":0.1838,"fb_pct_allowed":0.1961,"barrel_pct_allowed":0.0649},{"pitcher_id":657277,"season":2023,"avg_ip":6.28,"avg_k":6.0,"avg_bb":0.94,"avg_h":6.12,"avg_hr":0.594,"fip":2.92,"games_started":32,"updated_at":"2026-04-18T14:58:19.042981","hr9_vs_l":0.71,"hr9_vs_r":1.085,"k_pct_vs_l":0.2424,"k_pct_vs_r":0.2138,"fb_pct_allowed":0.168,"barrel_pct_allowed":0.0407},{"pitcher_id":657277,"season":2022,"avg_ip":5.68,"avg_k":5.09,"avg_bb":1.53,"avg_h":5.44,"avg_hr":0.344,"fip":2.93,"games_started":32,"updated_at":"2026-04-18T14:58:19.042981","hr9_vs_l":0.587,"hr9_vs_r":0.502,"k_pct_vs_l":0.19,"k_pct_vs_r":0.2231,"fb_pct_allowed":0.1922,"barrel_pct_allowed":0.0355},{"pitcher_id":657277,"season":2021,"avg_ip":5.32,"avg_k":6.04,"avg_bb":1.38,"avg_h":4.92,"avg_hr":0.346,"fip":2.56,"games_started":26,"updated_at":"2026-04-18T14:58:19.042981","hr9_vs_l":0.531,"hr9_vs_r":0.638,"k_pct_vs_l":0.226,"k_pct_vs_r":0.3026,"fb_pct_allowed":0.1497,"barrel_pct_allowed":0.0331},{"pitcher_id":657277,"season":2020,"avg_ip":4.03,"avg_k":3.83,"avg_bb":1.83,"avg_h":5.0,"avg_hr":0.333,"fip":3.9,"games_started":12,"updated_at":"2026-04-18T14:58:19.042981","hr9_vs_l":0.763,"hr9_vs_r":0.727,"k_pct_vs_l":0.1818,"k_pct_vs_r":0.189,"fb_pct_allowed":0.1775,"barrel_pct_allowed":0.0414}],"recentProj":[{"pitcher_id":657277,"game_pk":822752,"game_date":"2026-04-17","proj":{"h":6.5,"k":4.85,"bb":2.2,"er":2.13,"hr":0.4,"ip":5.87},"dk_pts":13.41,"fd_pts":20.53,"fip":3.2,"games_started":5,"stuff_signal":"0","model_version":"2.1","lineup_source":"confirmed","created_at":"2026-04-18T22:30:38.793015","side":"away","ml_dk_pts":16.77743110211497,"ml_fd_pts":26.33850868872617,"ml_delta":3.3674311021149705},{"pitcher_id":657277,"game_pk":824857,"game_date":"2026-04-11","proj":{"h":6.43,"k":5.26,"bb":2.2,"er":2.13,"hr":0.421,"ip":5.87},"dk_pts":14.29,"fd_pts":21.82,"fip":3.2,"games_started":5,"stuff_signal":"0","model_version":"2.1","lineup_source":"confirmed","created_at":"2026-04-18T22:30:29.484216","side":"away","ml_dk_pts":17.794937602034253,"ml_fd_pts":27.91815666654951,"ml_delta":3.5049376020342535},{"pitcher_id":657277,"game_pk":776550,"game_date":"2025-08-28","proj":{"h":6.22,"k":5.41,"bb":2.2,"er":1.98,"hr":0.331,"ip":5.87},"dk_pts":15.03,"fd_pts":22.87,"fip":3.2,"games_started":5,"stuff_signal":"0","model_version":"2.1","lineup_source":"confirmed","created_at":"2026-04-20T12:58:02.962573","side":"home","ml_dk_pts":null,"ml_fd_pts":null,"ml_delta":null},{"pitcher_id":657277,"game_pk":776621,"game_date":"2025-08-23","proj":{"h":5.78,"k":5.95,"bb":2.2,"er":2.24,"hr":0.458,"ip":5.87},"dk_pts":15.83,"fd_pts":23.95,"fip":3.2,"games_started":5,"stuff_signal":"0","model_version":"2.1","lineup_source":"confirmed","created_at":"2026-04-20T12:52:12.221407","side":"away","ml_dk_pts":null,"ml_fd_pts":null,"ml_delta":null},{"pitcher_id":657277,"game_pk":776703,"game_date":"2025-08-17","proj":{"h":6.22,"k":5.41,"bb":2.2,"er":2.12,"hr":0.355,"ip":5.87},"dk_pts":14.74,"fd_pts":22.44,"fip":3.2,"games_started":5,"stuff_signal":"0","model_version":"2.1","lineup_source":"confirmed","created_at":"2026-04-20T12:45:39.211914","side":"home","ml_dk_pts":null,"ml_fd_pts":null,"ml_delta":null},{"pitcher_id":657277,"game_pk":776780,"game_date":"2025-08-11","proj":{"h":6.22,"k":5.41,"bb":2.2,"er":2.09,"hr":0.351,"ip":5.87},"dk_pts":14.8,"fd_pts":22.53,"fip":3.2,"games_started":5,"stuff_signal":"0","model_version":"2.1","lineup_source":"confirmed","created_at":"2026-04-20T12:39:36.007452","side":"home","ml_dk_pts":null,"ml_fd_pts":null,"ml_delta":null},{"pitcher_id":657277,"game_pk":776866,"game_date":"2025-08-05","proj":{"h":6.17,"k":5.21,"bb":2.2,"er":1.87,"hr":0.305,"ip":5.87},"dk_pts":14.85,"fd_pts":22.59,"fip":3.2,"games_started":5,"stuff_signal":"0","model_version":"2.1","lineup_source":"confirmed","created_at":"2026-04-20T12:33:43.955155","side":"away","ml_dk_pts":null,"ml_fd_pts":null,"ml_delta":null}],"reconciled":[{"game_date":"2026-04-17","proj_dk_pts":13.41,"actual_dk_pts":20.1,"dk_error":6.69,"abs_dk_error":6.69,"actual":{"h":7,"k":6,"bb":2,"hr":1,"ip":6.0}},{"game_date":"2026-04-11","proj_dk_pts":14.29,"actual_dk_pts":20.7,"dk_error":6.41,"abs_dk_error":6.41,"actual":{"h":5,"k":6,"bb":3,"hr":1,"ip":6.0}},{"game_date":"2025-08-28","proj_dk_pts":15.03,"actual_dk_pts":23.3,"dk_error":8.27,"abs_dk_error":8.27,"actual":{"h":7,"k":7,"bb":0,"hr":2,"ip":6.0}},{"game_date":"2025-08-23","proj_dk_pts":15.83,"actual_dk_pts":17.8,"dk_error":1.97,"abs_dk_error":1.97,"actual":{"h":5,"k":5,"bb":2,"hr":0,"ip":5.33}},{"game_date":"2025-08-17","proj_dk_pts":14.74,"actual_dk_pts":27.2,"dk_error":12.46,"abs_dk_error":12.46,"actual":{"h":3,"k":7,"bb":0,"hr":0,"ip":6.67}},{"game_date":"2025-08-11","proj_dk_pts":14.8,"actual_dk_pts":14.85,"dk_error":0.05,"abs_dk_error":0.05,"actual":{"h":8,"k":3,"bb":1,"hr":1,"ip":6.33}},{"game_date":"2025-08-05","proj_dk_pts":14.85,"actual_dk_pts":29.3,"dk_error":14.45,"abs_dk_error":14.45,"actual":{"h":7,"k":10,"bb":0,"hr":0,"ip":6.0}}]}