{"player":{"player_id":664285,"full_name":"Framber Valdez","bat_side":null,"pitch_hand":"L","primary_position":null,"team_id":null,"active":true},"seasons":[{"pitcher_id":664285,"season":2026,"avg_ip":5.83,"avg_k":3.25,"avg_bb":1.75,"avg_h":6.0,"avg_hr":0.0,"fip":2.87,"games_started":4,"updated_at":"2026-04-18T14:58:19.042981","hr9_vs_l":null,"hr9_vs_r":0.0,"k_pct_vs_l":null,"k_pct_vs_r":0.1176,"fb_pct_allowed":0.2169,"barrel_pct_allowed":0.0361},{"pitcher_id":664285,"season":2025,"avg_ip":5.9,"avg_k":6.03,"avg_bb":2.19,"avg_h":5.52,"avg_hr":0.484,"fip":3.38,"games_started":31,"updated_at":"2026-04-18T14:58:19.042981","hr9_vs_l":1.299,"hr9_vs_r":0.607,"k_pct_vs_l":0.2171,"k_pct_vs_r":0.2366,"fb_pct_allowed":0.1889,"barrel_pct_allowed":0.0557},{"pitcher_id":664285,"season":2024,"avg_ip":5.88,"avg_k":6.04,"avg_bb":1.96,"avg_h":5.0,"avg_hr":0.464,"fip":3.21,"games_started":28,"updated_at":"2026-04-18T14:58:19.042981","hr9_vs_l":0.675,"hr9_vs_r":0.717,"k_pct_vs_l":0.2982,"k_pct_vs_r":0.2288,"fb_pct_allowed":0.1649,"barrel_pct_allowed":0.0514},{"pitcher_id":664285,"season":2023,"avg_ip":6.09,"avg_k":6.45,"avg_bb":1.84,"avg_h":5.35,"avg_hr":0.613,"fip":3.42,"games_started":31,"updated_at":"2026-04-18T14:58:19.042981","hr9_vs_l":null,"hr9_vs_r":null,"k_pct_vs_l":null,"k_pct_vs_r":null,"fb_pct_allowed":null,"barrel_pct_allowed":null},{"pitcher_id":664285,"season":2022,"avg_ip":6.16,"avg_k":6.26,"avg_bb":2.16,"avg_h":5.35,"avg_hr":0.355,"fip":2.98,"games_started":31,"updated_at":"2026-04-18T14:58:19.042981","hr9_vs_l":null,"hr9_vs_r":null,"k_pct_vs_l":null,"k_pct_vs_r":null,"fb_pct_allowed":null,"barrel_pct_allowed":null},{"pitcher_id":664285,"season":2021,"avg_ip":5.86,"avg_k":5.68,"avg_bb":2.64,"avg_h":5.0,"avg_hr":0.545,"fip":3.93,"games_started":22,"updated_at":"2026-04-18T14:58:19.042981","hr9_vs_l":null,"hr9_vs_r":null,"k_pct_vs_l":null,"k_pct_vs_r":null,"fb_pct_allowed":null,"barrel_pct_allowed":null},{"pitcher_id":664285,"season":2020,"avg_ip":6.12,"avg_k":6.91,"avg_bb":1.45,"avg_h":5.73,"avg_hr":0.455,"fip":2.61,"games_started":11,"updated_at":"2026-04-18T14:58:19.042981","hr9_vs_l":null,"hr9_vs_r":null,"k_pct_vs_l":null,"k_pct_vs_r":null,"fb_pct_allowed":null,"barrel_pct_allowed":null}],"recentProj":[{"pitcher_id":664285,"game_pk":824777,"game_date":"2026-04-19","proj":{"h":6.52,"k":3.17,"bb":1.75,"er":1.9,"hr":0,"ip":5.83},"dk_pts":10.68,"fd_pts":16.32,"fip":2.87,"games_started":4,"stuff_signal":"0","model_version":"2.1","lineup_source":"fallback","created_at":"2026-04-19T05:05:42.818927","side":"away","ml_dk_pts":null,"ml_fd_pts":null,"ml_delta":null},{"pitcher_id":664285,"game_pk":824292,"game_date":"2026-04-14","proj":{"h":5.93,"k":3.2,"bb":1.75,"er":1.94,"hr":0,"ip":5.83},"dk_pts":11.02,"fd_pts":16.65,"fip":2.87,"games_started":4,"stuff_signal":"0","model_version":"2.1","lineup_source":"confirmed","created_at":"2026-04-18T22:30:34.231428","side":"home","ml_dk_pts":18.78566888391084,"ml_fd_pts":29.82675722586936,"ml_delta":7.765668883910841},{"pitcher_id":664285,"game_pk":776571,"game_date":"2025-08-27","proj":{"h":5.92,"k":3.29,"bb":1.75,"er":1.88,"hr":0,"ip":5.83},"dk_pts":11.32,"fd_pts":17.1,"fip":2.87,"games_started":4,"stuff_signal":"0","model_version":"2.1","lineup_source":"confirmed","created_at":"2026-04-20T12:56:48.569058","side":"home","ml_dk_pts":null,"ml_fd_pts":null,"ml_delta":null},{"pitcher_id":664285,"game_pk":776673,"game_date":"2025-08-20","proj":{"h":5.93,"k":3.2,"bb":1.75,"er":1.89,"hr":0,"ip":5.83},"dk_pts":11.13,"fd_pts":16.81,"fip":2.87,"games_started":4,"stuff_signal":"0","model_version":"2.1","lineup_source":"confirmed","created_at":"2026-04-20T12:49:05.325726","side":"away","ml_dk_pts":null,"ml_fd_pts":null,"ml_delta":null},{"pitcher_id":664285,"game_pk":776733,"game_date":"2025-08-15","proj":{"h":5.92,"k":3.29,"bb":1.75,"er":1.88,"hr":0,"ip":5.83},"dk_pts":11.32,"fd_pts":17.1,"fip":2.87,"games_started":4,"stuff_signal":"0","model_version":"2.1","lineup_source":"confirmed","created_at":"2026-04-20T12:43:23.591484","side":"home","ml_dk_pts":null,"ml_fd_pts":null,"ml_delta":null},{"pitcher_id":664285,"game_pk":776815,"game_date":"2025-08-09","proj":{"h":5.62,"k":3.42,"bb":1.75,"er":2.16,"hr":0,"ip":5.83},"dk_pts":11.22,"fd_pts":16.86,"fip":2.87,"games_started":4,"stuff_signal":"0","model_version":"2.1","lineup_source":"confirmed","created_at":"2026-04-20T12:37:15.475605","side":"away","ml_dk_pts":null,"ml_fd_pts":null,"ml_delta":null},{"pitcher_id":664285,"game_pk":776895,"game_date":"2025-08-03","proj":{"h":6.52,"k":3.17,"bb":1.75,"er":1.96,"hr":0,"ip":5.83},"dk_pts":10.56,"fd_pts":16.14,"fip":2.87,"games_started":4,"stuff_signal":"0","model_version":"2.1","lineup_source":"confirmed","created_at":"2026-04-20T12:31:50.692264","side":"away","ml_dk_pts":null,"ml_fd_pts":null,"ml_delta":null}],"reconciled":[{"game_date":"2026-04-19","proj_dk_pts":10.68,"actual_dk_pts":24.5,"dk_error":13.82,"abs_dk_error":13.82,"actual":{"h":3,"k":7,"bb":2,"hr":1,"ip":6.0}},{"game_date":"2026-04-14","proj_dk_pts":11.02,"actual_dk_pts":13.4,"dk_error":2.38,"abs_dk_error":2.38,"actual":{"h":4,"k":1,"bb":2,"hr":0,"ip":6.67}},{"game_date":"2025-08-27","proj_dk_pts":11.32,"actual_dk_pts":22.0,"dk_error":10.68,"abs_dk_error":10.68,"actual":{"h":3,"k":5,"bb":2,"hr":0,"ip":6.67}},{"game_date":"2025-08-20","proj_dk_pts":11.13,"actual_dk_pts":7.15,"dk_error":-3.98,"abs_dk_error":3.98,"actual":{"h":7,"k":2,"bb":4,"hr":0,"ip":4.33}},{"game_date":"2025-08-15","proj_dk_pts":11.32,"actual_dk_pts":21.0,"dk_error":9.68,"abs_dk_error":9.68,"actual":{"h":9,"k":6,"bb":1,"hr":1,"ip":6.67}},{"game_date":"2025-08-09","proj_dk_pts":11.22,"actual_dk_pts":6.05,"dk_error":-5.17,"abs_dk_error":5.17,"actual":{"h":8,"k":1,"bb":4,"hr":0,"ip":5.0}},{"game_date":"2025-08-03","proj_dk_pts":10.56,"actual_dk_pts":13.95,"dk_error":3.39,"abs_dk_error":3.39,"actual":{"h":7,"k":3,"bb":1,"hr":0,"ip":5.67}}]}